{"gsRQJZiFqskggWtRhNgGuw==":"product_logo_-_black-96x70.png","iGfwYwCif79/LZB1PR4b/A==":"covid-19_vaccinekids-800x500.jpg","ODdKIck/LYkEA1J60JFAnA==":"mbr-1920x1459.jpg","92WdNfyUv2PfQ2TD+l6e0w==":"mbr-1920x1394.jpg","2wYX1P4sl+inLjWriGF8DQ==":"mbr-1920x1271.jpg","Ny1TSSPJYOiz1kz7E1CMmw==":"contact-us-customer-support-hotline-people-connect-call-customer-support_36325-1640-626x417.jpg","oGoTgfEYZsuaRc5E7dGfZw==":"mbr-1920x905.jpg","anLY2L3pzN6ob9A863a5xw==":"pexels-pixabay-263564-2000x1000.jpg","eVPWnFZ3mL8Ufgltv4rX3w==":"pexels-negative-space-34000-2000x1334.jpg","iuCSlIDtCXPTASdSfxXTxw==":"pexels-alex-andrews-821754-2000x1500.jpg"}